{
    "basics": {
      "name": "Palukoori SaiCharan",
      "image": "",
      "email": "palukoorisaicharan@gmail.com",
      "phone": "(630) 572-1481",
      "location": {
        "address": "1-24,V.R.Kandriga village",
        "postalCode": "517588",
        "District": "Chittoor",
        "State": "Andhra Pradesh",
        "region": "India"
      }
    },
    "work": [{
      "name": "Turning point software solutions",
      "position": "Junior provisioning analyst",
      "startDate": "2020-01-07",
      "endDate": "200-07-31"
      
    }],
    
    "education": [{
      "institution": "RVS Padmavathy College of Engineering and Technology",
      "area": "Chedilpakkam",
      "studyType": "BE",
      "startDate": "2015-06-12",
      "endDate": "2019-06-09",
      "CGP": "6.7"
      
    }],
   
    "skills": [{
      "Department": "Mechanical Engineering",
      "keywords": [
        "CADD 2D"
      ]
    }],
    "languages": [{
      "language": "English,Hindi,Tamil,Telugu",
      "fluency": "Native speaker"
    }],
    "interests": [{
      "name": "kabaddi,drawing"
      
    }],
    "references": [{
      "name": "Palukoori SaiCharan",
      "reference": "palukoorisaicharan@gmail.com"
    }],
    "projects": [{
      "name": "Electricity generation using railway track",
      "description":"aim of the project is generate electricty by using rack and pinion mechanism",
      "roles": [
        "Team Lead"
      ]
      
    }]
  }